ai_tools/__init__.py
ai_tools/file_system/get_file_data.py
akhera_ai_tools-0.1.0.dist-info/licenses/LICENSE
akhera_ai_tools-0.1.0.dist-info/METADATA
akhera_ai_tools-0.1.0.dist-info/WHEEL
akhera_ai_tools-0.1.0.dist-info/top_level.txt
akhera_ai_tools-0.1.0.dist-info/RECORD
