Metadata-Version: 2.4
Name: akhera-ai-tools
Version: 0.1.0
Summary: AI tooling utilities
Author: Your Name
Author-email: Your Name <your.email@example.com>
License: MIT
Project-URL: Homepage, https://github.com/yourusername/ai-tools
Project-URL: Bug Tracker, https://github.com/yourusername/ai-tools/issues
Requires-Python: >=3.6
License-File: LICENSE
Requires-Dist: pypdf<5.0.0,>=4.0.0
Dynamic: author
Dynamic: license-file
Dynamic: requires-python
